openai_router/__init__.py
openai_router/main.py
openai_router-0.1.3.dist-info/licenses/LICENSE.txt
openai_router-0.1.3.dist-info/METADATA
openai_router-0.1.3.dist-info/WHEEL
openai_router-0.1.3.dist-info/entry_points.txt
openai_router-0.1.3.dist-info/top_level.txt
openai_router-0.1.3.dist-info/RECORD
