Metadata-Version: 2.4
Name: openai-router
Version: 0.1.3
Summary: openai-router
Requires-Python: >=3.11
License-File: LICENSE.txt
Requires-Dist: fastapi>=0.120.3
Requires-Dist: gradio>=5.49.1
Requires-Dist: httpx>=0.28.1
Requires-Dist: loguru>=0.7.3
Requires-Dist: sqlmodel>=0.0.27
Requires-Dist: uvicorn>=0.38.0
Dynamic: license-file
